pydentate/__init__.py
pydentate/analyze.py
pydentate/predict.py
pydentate/pydentate_lite.py
pydentate/models/__init__.py
pydentate/models/coordinating_atoms.pt
pydentate/models/coordination_number.pt
pydentate/models/hemilability.pt
pydentate-1.1.3.dist-info/licenses/LICENSE
pydentate-1.1.3.dist-info/METADATA
pydentate-1.1.3.dist-info/WHEEL
pydentate-1.1.3.dist-info/top_level.txt
pydentate-1.1.3.dist-info/RECORD
